thoughtful/__init__.py
thoughtful/__version__.py
thoughtful/environment_variables.py
thoughtful/screen_recorder/__init__.py
thoughtful/screen_recorder/browser_manager.py
thoughtful/screen_recorder/screen_recorder.py
thoughtful/supervisor/__init__.py
thoughtful/supervisor/default_instances.py
thoughtful/supervisor/event_bus.py
thoughtful/supervisor/main_context.py
thoughtful/supervisor/manifest.py
thoughtful/supervisor/py.typed
thoughtful/supervisor/reporting/__init__.py
thoughtful/supervisor/reporting/record.py
thoughtful/supervisor/reporting/record_report.py
thoughtful/supervisor/reporting/report.py
thoughtful/supervisor/reporting/report_builder.py
thoughtful/supervisor/reporting/status.py
thoughtful/supervisor/reporting/step_report.py
thoughtful/supervisor/reporting/timed_report.py
thoughtful/supervisor/reporting/timer.py
thoughtful/supervisor/step_context.py
thoughtful/supervisor/step_decorator_factory.py
thoughtful/supervisor/streaming/__init__.py
thoughtful/supervisor/streaming/action.py
thoughtful/supervisor/streaming/jwt_auth.py
thoughtful/supervisor/streaming/payloads.py
thoughtful/supervisor/streaming/streamer.py
thoughtful/supervisor/streaming/token.py
thoughtful/supervisor/telemetry/__init__.py
thoughtful/supervisor/telemetry/common.py
thoughtful/supervisor/telemetry/config.py
thoughtful/supervisor/telemetry/exclusions.py
thoughtful/supervisor/telemetry/logging/__init__.py
thoughtful/supervisor/telemetry/logging/config.py
thoughtful/supervisor/telemetry/meter_utils.py
thoughtful/supervisor/telemetry/metrics/__init__.py
thoughtful/supervisor/telemetry/metrics/config.py
thoughtful/supervisor/telemetry/metrics/counters.py
thoughtful/supervisor/telemetry/metrics/gauges.py
thoughtful/supervisor/telemetry/metrics/histograms.py
thoughtful/supervisor/telemetry/span_processors.py
thoughtful/supervisor/telemetry/tracing/__init__.py
thoughtful/supervisor/telemetry/tracing/auth.py
thoughtful/supervisor/telemetry/tracing/config.py
thoughtful-3.2.3.dist-info/LICENSE
thoughtful-3.2.3.dist-info/METADATA
thoughtful-3.2.3.dist-info/WHEEL
thoughtful-3.2.3.dist-info/RECORD
