Metadata-Version: 2.1
Name: thoughtful
Version: 3.2.3
Summary: Thoughtful is a python package by Thoughtful for helping manage automations with helpful packages like supervisor
Home-page: https://thoughtful.ai
License: Apache-2.0
Keywords: rpa,robot-framework,robocorp,automation
Author: Thoughtful Automation
Author-email: care@thoughtful.ai
Requires-Python: >=3.10,<3.13
Classifier: Framework :: Robot Framework
Classifier: Framework :: Robot Framework :: Library
Classifier: Framework :: Robot Framework :: Tool
Classifier: License :: OSI Approved :: Apache Software License
Classifier: Programming Language :: Python :: 3
Classifier: Programming Language :: Python :: 3.10
Classifier: Programming Language :: Python :: 3.11
Classifier: Topic :: Security :: Cryptography
Provides-Extra: screen-recorder
Provides-Extra: t-vault
Requires-Dist: aws-requests-auth (>=0.4.3,<0.5.0)
Requires-Dist: boto3 (>=1.24.64,<2.0.0)
Requires-Dist: chevron (>=0.14.0,<0.15.0)
Requires-Dist: grpcio (>=1.60.0,<2.0.0)
Requires-Dist: httpx (>=0.28.1,<0.29.0)
Requires-Dist: imageio (>=2.34.2,<3.0.0) ; extra == "screen-recorder"
Requires-Dist: imageio-ffmpeg (>=0.5.1,<0.6.0) ; extra == "screen-recorder"
Requires-Dist: isodate (>=0.6.1,<0.7.0)
Requires-Dist: moto (>=4.0.5,<5.0.0)
Requires-Dist: numpy (>=1.24.4,<2.0.0) ; extra == "screen-recorder"
Requires-Dist: opentelemetry-api (>=1.37.0,<2.0.0)
Requires-Dist: opentelemetry-exporter-otlp-proto-grpc (>=1.37.0,<2.0.0)
Requires-Dist: opentelemetry-exporter-otlp-proto-http (>=1.37.0,<2.0.0)
Requires-Dist: opentelemetry-instrumentation-grpc (>=0.58b0,<0.59)
Requires-Dist: opentelemetry-instrumentation-httpx (>=0.58b0,<0.59)
Requires-Dist: opentelemetry-instrumentation-requests (>=0.58b0,<0.59)
Requires-Dist: opentelemetry-sdk (>=1.37.0,<2.0.0)
Requires-Dist: pillow (>=10.4.0,<11.0.0) ; extra == "screen-recorder"
Requires-Dist: pyconfs (>=0.5.5,<0.6.0)
Requires-Dist: pydantic (>=2.5.2,<3.0.0)
Requires-Dist: pyjwt (>=2.9.0,<3.0.0)
Requires-Dist: pyyaml (>=5.4.1)
Requires-Dist: requests (>=2.28.1,<3.0.0)
Requires-Dist: robotframework-seleniumlibrary (>=6.5.0,<7.0.0) ; extra == "screen-recorder"
Requires-Dist: t-vault-manager (>=0.1.20,<0.2.0) ; extra == "t-vault"
Project-URL: Documentation, https://www.notion.so/thoughtfulautomation/Thoughtful-Library-c0333f67989d4044aa0a595eaf8fd07b
Project-URL: Repository, https://github.com/thoughtful-automation/thoughtful
